[
    {
        "filename": ".\\PhabricatorAuthSessionEngine.php",
        "name": ".\\PhabricatorAuthSessionEngine.php",
        "loc": 813,
        "logicalLoc": 160,
        "volume": 10913.01,
        "length": 1374,
        "vocabulary": 246,
        "effort": 574448.98,
        "difficulty": "52.64",
        "time": 31914,
        "bugs": 3.64,
        "intelligentContent": 207.32,
        "maintainabilityIndexWithoutComment": "15.84",
        "maintainabilityIndex": "51.78",
        "commentWeight": 35.94,
        "instability": 0.89,
        "afferentCoupling": 3,
        "efferentCoupling": 25,
        "noc": 1,
        "noca": 0,
        "nocc": 1,
        "noc-anon": 0,
        "noi": 0,
        "nom": 15,
        "cyclomaticComplexity": 58,
        "myerInterval": "58:60",
        "myerDistance": 2,
        "operators": 2,
        "lcom": 11,
        "sysc": 307.22,
        "rsysc": 20.48,
        "dc": 12.22,
        "rdc": 0.81,
        "sc": 295,
        "rsc": 19.67
    },
    {
        "filename": ".\\PhabricatorController.php",
        "name": ".\\PhabricatorController.php",
        "loc": 613,
        "logicalLoc": 163,
        "volume": 11862.66,
        "length": 1445,
        "vocabulary": 296,
        "effort": 281536.21,
        "difficulty": "23.73",
        "time": 15641,
        "bugs": 3.95,
        "intelligentContent": 499.84,
        "maintainabilityIndexWithoutComment": "13.53",
        "maintainabilityIndex": "35.33",
        "commentWeight": 21.8,
        "instability": 1,
        "afferentCoupling": 0,
        "efferentCoupling": 42,
        "noc": 1,
        "noca": 1,
        "nocc": 0,
        "noc-anon": 0,
        "noi": 0,
        "nom": 29,
        "cyclomaticComplexity": 72,
        "myerInterval": "72:85",
        "myerDistance": 13,
        "operators": 13,
        "lcom": 13,
        "sysc": 612.59,
        "rsysc": 21.12,
        "dc": 28.59,
        "rdc": 0.99,
        "sc": 584,
        "rsc": 20.14
    },
    {
        "filename": ".\\PhabricatorUser.php",
        "name": ".\\PhabricatorUser.php",
        "loc": 1536,
        "logicalLoc": 369,
        "volume": 25928.15,
        "length": 2872,
        "vocabulary": 522,
        "effort": 1365690.71,
        "difficulty": "52.67",
        "time": 75872,
        "bugs": 8.64,
        "intelligentContent": 492.26,
        "maintainabilityIndexWithoutComment": "0",
        "maintainabilityIndex": "28.48",
        "commentWeight": 28.48,
        "instability": 0.9,
        "afferentCoupling": 5,
        "efferentCoupling": 46,
        "noc": 1,
        "noca": 0,
        "nocc": 1,
        "noc-anon": 0,
        "noi": 0,
        "nom": 92,
        "cyclomaticComplexity": 111,
        "myerInterval": "111:114",
        "myerDistance": 3,
        "operators": 3,
        "lcom": 47,
        "sysc": 360.84000000000003,
        "rsysc": 3.92,
        "dc": 107.84,
        "rdc": 1.17,
        "sc": 253,
        "rsc": 2.75
    },
    {
        "filename": ".\\PhabricatorUserCache.php",
        "name": ".\\PhabricatorUserCache.php",
        "loc": 109,
        "logicalLoc": 26,
        "volume": 1043.18,
        "length": 183,
        "vocabulary": 52,
        "effort": 13288.13,
        "difficulty": "12.74",
        "time": 738,
        "bugs": 0.35,
        "intelligentContent": 81.89,
        "maintainabilityIndexWithoutComment": "47.46",
        "maintainabilityIndex": "47.46",
        "commentWeight": 0,
        "instability": 0.58,
        "afferentCoupling": 5,
        "efferentCoupling": 7,
        "noc": 1,
        "noca": 0,
        "nocc": 1,
        "noc-anon": 0,
        "noi": 0,
        "nom": 5,
        "cyclomaticComplexity": 4,
        "myerInterval": "4:4",
        "myerDistance": 0,
        "operators": 0,
        "lcom": 5,
        "sysc": 66.93,
        "rsysc": 13.39,
        "dc": 1.93,
        "rdc": 0.39,
        "sc": 65,
        "rsc": 13
    },
    {
        "filename": ".\\PhabricatorUserCacheType.php",
        "name": ".\\PhabricatorUserCacheType.php",
        "loc": 69,
        "logicalLoc": 15,
        "volume": 597.59,
        "length": 107,
        "vocabulary": 48,
        "effort": 6325.93,
        "difficulty": "10.59",
        "time": 351,
        "bugs": 0.2,
        "intelligentContent": 56.45,
        "maintainabilityIndexWithoutComment": "54.37",
        "maintainabilityIndex": "54.37",
        "commentWeight": 0,
        "instability": 0.5,
        "afferentCoupling": 4,
        "efferentCoupling": 4,
        "noc": 1,
        "noca": 1,
        "nocc": 0,
        "noc-anon": 0,
        "noi": 0,
        "nom": 11,
        "cyclomaticComplexity": 4,
        "myerInterval": "4:4",
        "myerDistance": 0,
        "operators": 0,
        "lcom": 11,
        "sysc": 22.17,
        "rsysc": 2.02,
        "dc": 15.17,
        "rdc": 1.38,
        "sc": 7,
        "rsc": 0.64
    },
    {
        "filename": ".\\PhabricatorUserPreferences.php",
        "name": ".\\PhabricatorUserPreferences.php",
        "loc": 257,
        "logicalLoc": 88,
        "volume": 3980.04,
        "length": 547,
        "vocabulary": 155,
        "effort": 72006.53,
        "difficulty": "18.09",
        "time": 4000,
        "bugs": 1.33,
        "intelligentContent": 219.99,
        "maintainabilityIndexWithoutComment": "30.22",
        "maintainabilityIndex": "44.51",
        "commentWeight": 14.29,
        "instability": 0.88,
        "afferentCoupling": 2,
        "efferentCoupling": 15,
        "noc": 1,
        "noca": 0,
        "nocc": 1,
        "noc-anon": 0,
        "noi": 0,
        "nom": 22,
        "cyclomaticComplexity": 16,
        "myerInterval": "16:17",
        "myerDistance": 1,
        "operators": 1,
        "lcom": 15,
        "sysc": 66.75,
        "rsysc": 3.03,
        "dc": 29.75,
        "rdc": 1.35,
        "sc": 37,
        "rsc": 1.68
    },
    {
        "filename": ".\\PhabricatorUserPreferencesCacheType.php",
        "name": ".\\PhabricatorUserPreferencesCacheType.php",
        "loc": 30,
        "logicalLoc": 7,
        "volume": 274.79,
        "length": 56,
        "vocabulary": 30,
        "effort": 1825.36,
        "difficulty": "6.64",
        "time": 101,
        "bugs": 0.09,
        "intelligentContent": 41.37,
        "maintainabilityIndexWithoutComment": "64.35",
        "maintainabilityIndex": "64.35",
        "commentWeight": 0,
        "instability": 0.33,
        "afferentCoupling": 4,
        "efferentCoupling": 2,
        "noc": 1,
        "noca": 0,
        "nocc": 1,
        "noc-anon": 0,
        "noi": 0,
        "nom": 3,
        "cyclomaticComplexity": 1,
        "myerInterval": "1:1",
        "myerDistance": 0,
        "operators": 0,
        "lcom": 3,
        "sysc": 6,
        "rsysc": 2,
        "dc": 3,
        "rdc": 1,
        "sc": 3,
        "rsc": 1
    },
    {
        "filename": ".\\PhabricatorUserPreferencesEditor.php",
        "name": ".\\PhabricatorUserPreferencesEditor.php",
        "loc": 153,
        "logicalLoc": 39,
        "volume": 2092.88,
        "length": 336,
        "vocabulary": 75,
        "effort": 66392.98,
        "difficulty": "31.72",
        "time": 3688,
        "bugs": 0.7,
        "intelligentContent": 65.97,
        "maintainabilityIndexWithoutComment": "40.43",
        "maintainabilityIndex": "40.43",
        "commentWeight": 0,
        "instability": 0.89,
        "afferentCoupling": 1,
        "efferentCoupling": 8,
        "noc": 1,
        "noca": 0,
        "nocc": 1,
        "noc-anon": 0,
        "noi": 0,
        "nom": 9,
        "cyclomaticComplexity": 12,
        "myerInterval": "12:12",
        "myerDistance": 0,
        "operators": 0,
        "lcom": 9,
        "sysc": 117.42,
        "rsysc": 13.05,
        "dc": 6.42,
        "rdc": 0.71,
        "sc": 111,
        "rsc": 12.33
    }
]