[
    {
        "filename": ".\\AphrontFormTokenizerControl.php",
        "name": ".\\AphrontFormTokenizerControl.php",
        "loc": 106,
        "logicalLoc": 33,
        "volume": 1326.96,
        "length": 222,
        "vocabulary": 63,
        "effort": 19826.29,
        "difficulty": "14.94",
        "time": 1101,
        "bugs": 0.44,
        "intelligentContent": 88.81,
        "maintainabilityIndexWithoutComment": "44.2",
        "maintainabilityIndex": "44.2",
        "commentWeight": 0,
        "instability": 0.5,
        "afferentCoupling": 3,
        "efferentCoupling": 3,
        "noc": 1,
        "noca": 0,
        "nocc": 1,
        "noc-anon": 0,
        "noi": 0,
        "nom": 7,
        "cyclomaticComplexity": 6,
        "myerInterval": "6:6",
        "myerDistance": 0,
        "operators": 0,
        "lcom": 2,
        "sysc": 20.25,
        "rsysc": 2.89,
        "dc": 11.25,
        "rdc": 1.61,
        "sc": 9,
        "rsc": 1.29
    },
    {
        "filename": ".\\default.conf.php",
        "name": ".\\default.conf.php",
        "loc": 1128,
        "logicalLoc": 1,
        "volume": 812.67,
        "length": 175,
        "vocabulary": 25,
        "effort": 15440.82,
        "difficulty": "19",
        "time": 858,
        "bugs": 0.27,
        "intelligentContent": 42.77,
        "maintainabilityIndexWithoutComment": "79.22",
        "maintainabilityIndex": "126.06",
        "commentWeight": 46.84,
        "instability": 0,
        "afferentCoupling": 0,
        "efferentCoupling": 0,
        "noc": 0,
        "noca": 0,
        "nocc": 0,
        "noc-anon": 0,
        "noi": 0,
        "nom": 0,
        "cyclomaticComplexity": 3,
        "myerInterval": "3:3",
        "myerDistance": 0,
        "operators": 0,
        "lcom": 0,
        "sysc": 0,
        "rsysc": 0,
        "dc": 0,
        "rdc": 0,
        "sc": 0,
        "rsc": 0
    },
    {
        "filename": ".\\DifferentialAddCommentView.php",
        "name": ".\\DifferentialAddCommentView.php",
        "loc": 204,
        "logicalLoc": 47,
        "volume": 3093.06,
        "length": 457,
        "vocabulary": 109,
        "effort": 65151.69,
        "difficulty": "21.06",
        "time": 3620,
        "bugs": 1.03,
        "intelligentContent": 146.84,
        "maintainabilityIndexWithoutComment": "36.93",
        "maintainabilityIndex": "36.93",
        "commentWeight": 0,
        "instability": 1,
        "afferentCoupling": 0,
        "efferentCoupling": 12,
        "noc": 1,
        "noca": 0,
        "nocc": 1,
        "noc-anon": 0,
        "noi": 0,
        "nom": 8,
        "cyclomaticComplexity": 16,
        "myerInterval": "16:16",
        "myerDistance": 0,
        "operators": 0,
        "lcom": 1,
        "sysc": 135.08,
        "rsysc": 16.89,
        "dc": 13.08,
        "rdc": 1.64,
        "sc": 122,
        "rsc": 15.25
    },
    {
        "filename": ".\\DiffusionCommitController.php",
        "name": ".\\DiffusionCommitController.php",
        "loc": 1154,
        "logicalLoc": 383,
        "volume": 29276.82,
        "length": 3254,
        "vocabulary": 511,
        "effort": 1509578.54,
        "difficulty": "51.56",
        "time": 83865,
        "bugs": 9.76,
        "intelligentContent": 567.8,
        "maintainabilityIndexWithoutComment": "0",
        "maintainabilityIndex": "14.73",
        "commentWeight": 14.73,
        "instability": 0.98,
        "afferentCoupling": 1,
        "efferentCoupling": 65,
        "noc": 1,
        "noca": 0,
        "nocc": 1,
        "noc-anon": 0,
        "noi": 0,
        "nom": 13,
        "cyclomaticComplexity": 116,
        "myerInterval": "116:122",
        "myerDistance": 6,
        "operators": 6,
        "lcom": 3,
        "sysc": 1305.29,
        "rsysc": 100.41,
        "dc": 7.29,
        "rdc": 0.56,
        "sc": 1298,
        "rsc": 99.85
    },
    {
        "filename": ".\\ManiphestTaskDetailController.php",
        "name": ".\\ManiphestTaskDetailController.php",
        "loc": 721,
        "logicalLoc": 172,
        "volume": 15943.26,
        "length": 1920,
        "vocabulary": 316,
        "effort": 564536.31,
        "difficulty": "35.41",
        "time": 31363,
        "bugs": 5.31,
        "intelligentContent": 450.26,
        "maintainabilityIndexWithoutComment": "14.81",
        "maintainabilityIndex": "25.14",
        "commentWeight": 10.33,
        "instability": 1,
        "afferentCoupling": 0,
        "efferentCoupling": 41,
        "noc": 1,
        "noca": 0,
        "nocc": 1,
        "noc-anon": 0,
        "noi": 0,
        "nom": 7,
        "cyclomaticComplexity": 52,
        "myerInterval": "52:53",
        "myerDistance": 1,
        "operators": 1,
        "lcom": 2,
        "sysc": 1067.9,
        "rsysc": 152.56,
        "dc": 3.9,
        "rdc": 0.56,
        "sc": 1064,
        "rsc": 152
    },
    {
        "filename": ".\\map.php",
        "name": ".\\map.php",
        "loc": 2189,
        "logicalLoc": 1,
        "volume": 5917.06,
        "length": 1038,
        "vocabulary": 52,
        "effort": 122601.41,
        "difficulty": "20.72",
        "time": 6811,
        "bugs": 1.97,
        "intelligentContent": 285.57,
        "maintainabilityIndexWithoutComment": "73.45",
        "maintainabilityIndex": "76.76",
        "commentWeight": 3.31,
        "instability": 0,
        "afferentCoupling": 0,
        "efferentCoupling": 0,
        "noc": 0,
        "noca": 0,
        "nocc": 0,
        "noc-anon": 0,
        "noi": 0,
        "nom": 0,
        "cyclomaticComplexity": 1,
        "myerInterval": "1:1",
        "myerDistance": 0,
        "operators": 0,
        "lcom": 0,
        "sysc": 0,
        "rsysc": 0,
        "dc": 0,
        "rdc": 0,
        "sc": 0,
        "rsc": 0
    },
    {
        "filename": ".\\PhabricatorCoreConfigOptions.php",
        "name": ".\\PhabricatorCoreConfigOptions.php",
        "loc": 275,
        "logicalLoc": 18,
        "volume": 2549.42,
        "length": 443,
        "vocabulary": 54,
        "effort": 98214.66,
        "difficulty": "38.52",
        "time": 5456,
        "bugs": 0.85,
        "intelligentContent": 66.18,
        "maintainabilityIndexWithoutComment": "47.29",
        "maintainabilityIndex": "51.95",
        "commentWeight": 4.66,
        "instability": 1,
        "afferentCoupling": 0,
        "efferentCoupling": 3,
        "noc": 1,
        "noca": 0,
        "nocc": 1,
        "noc-anon": 0,
        "noi": 0,
        "nom": 4,
        "cyclomaticComplexity": 11,
        "myerInterval": "11:14",
        "myerDistance": 3,
        "operators": 3,
        "lcom": 4,
        "sysc": 11.5,
        "rsysc": 2.88,
        "dc": 2.5,
        "rdc": 0.63,
        "sc": 9,
        "rsc": 2.25
    },
    {
        "filename": ".\\PhabricatorSetupCheckExtraConfig.php",
        "name": ".\\PhabricatorSetupCheckExtraConfig.php",
        "loc": 184,
        "logicalLoc": 36,
        "volume": 1576,
        "length": 258,
        "vocabulary": 69,
        "effort": 29549.99,
        "difficulty": "18.75",
        "time": 1642,
        "bugs": 0.53,
        "intelligentContent": 84.05,
        "maintainabilityIndexWithoutComment": "42.18",
        "maintainabilityIndex": "53.5",
        "commentWeight": 11.32,
        "instability": 0.75,
        "afferentCoupling": 1,
        "efferentCoupling": 3,
        "noc": 1,
        "noca": 0,
        "nocc": 1,
        "noc-anon": 0,
        "noi": 0,
        "nom": 2,
        "cyclomaticComplexity": 11,
        "myerInterval": "11:11",
        "myerDistance": 0,
        "operators": 0,
        "lcom": 2,
        "sysc": 10,
        "rsysc": 5,
        "dc": 1,
        "rdc": 0.5,
        "sc": 9,
        "rsc": 4.5
    }
]