[
    {
        "filename": ".\\AbstractView.php",
        "name": ".\\AbstractView.php",
        "loc": 0,
        "logicalLoc": 0,
        "volume": 0,
        "length": 0,
        "vocabulary": 0,
        "effort": 0,
        "difficulty": "0",
        "time": 0,
        "bugs": 0,
        "intelligentContent": 0,
        "maintainabilityIndexWithoutComment": "171",
        "maintainabilityIndex": "171",
        "commentWeight": 0,
        "instability": 0,
        "afferentCoupling": 0,
        "efferentCoupling": 0,
        "noc": 0,
        "noca": 0,
        "nocc": 0,
        "noc-anon": 0,
        "noi": 0,
        "nom": 0,
        "cyclomaticComplexity": 1,
        "myerInterval": "1:1",
        "myerDistance": 0,
        "operators": 0,
        "lcom": 0,
        "sysc": 0,
        "rsysc": 0,
        "dc": 0,
        "rdc": 0,
        "sc": 0,
        "rsc": 0
    },
    {
        "filename": ".\\HelperBroker.php",
        "name": ".\\HelperBroker.php",
        "loc": 102,
        "logicalLoc": 12,
        "volume": 358.2,
        "length": 73,
        "vocabulary": 30,
        "effort": 2800.5,
        "difficulty": "7.82",
        "time": 156,
        "bugs": 0.12,
        "intelligentContent": 45.82,
        "maintainabilityIndexWithoutComment": "58.17",
        "maintainabilityIndex": "105.08",
        "commentWeight": 46.91,
        "instability": 0.75,
        "afferentCoupling": 1,
        "efferentCoupling": 3,
        "noc": 1,
        "noca": 0,
        "nocc": 1,
        "noc-anon": 0,
        "noi": 0,
        "nom": 4,
        "cyclomaticComplexity": 3,
        "myerInterval": "3:3",
        "myerDistance": 0,
        "operators": 0,
        "lcom": 2,
        "sysc": 7.5,
        "rsysc": 1.88,
        "dc": 4.5,
        "rdc": 1.13,
        "sc": 3,
        "rsc": 0.75
    },
    {
        "filename": ".\\PhpRenderer.php",
        "name": ".\\PhpRenderer.php",
        "loc": 286,
        "logicalLoc": 47,
        "volume": 2243.01,
        "length": 359,
        "vocabulary": 76,
        "effort": 46515.67,
        "difficulty": "20.74",
        "time": 2584,
        "bugs": 0.75,
        "intelligentContent": 108.16,
        "maintainabilityIndexWithoutComment": "36.97",
        "maintainabilityIndex": "80.5",
        "commentWeight": 43.53,
        "instability": 1,
        "afferentCoupling": 0,
        "efferentCoupling": 7,
        "noc": 1,
        "noca": 0,
        "nocc": 1,
        "noc-anon": 0,
        "noi": 0,
        "nom": 12,
        "cyclomaticComplexity": 23,
        "myerInterval": "23:24",
        "myerDistance": 1,
        "operators": 1,
        "lcom": 3,
        "sysc": 28.33,
        "rsysc": 2.36,
        "dc": 14.33,
        "rdc": 1.19,
        "sc": 14,
        "rsc": 1.17
    },
    {
        "filename": ".\\Renderer.php",
        "name": ".\\Renderer.php",
        "loc": 54,
        "logicalLoc": 3,
        "volume": 25.27,
        "length": 9,
        "vocabulary": 7,
        "effort": 12.63,
        "difficulty": "0.5",
        "time": 1,
        "bugs": 0.01,
        "intelligentContent": 50.53,
        "maintainabilityIndexWithoutComment": "79.64",
        "maintainabilityIndex": "129.03",
        "commentWeight": 49.39,
        "instability": 0,
        "afferentCoupling": 0,
        "efferentCoupling": 0,
        "noc": 1,
        "noca": 1,
        "nocc": 0,
        "noc-anon": 0,
        "noi": 1,
        "nom": 2,
        "cyclomaticComplexity": 1,
        "myerInterval": "1:1",
        "myerDistance": 0,
        "operators": 0,
        "lcom": 0,
        "sysc": 1,
        "rsysc": 0.5,
        "dc": 1,
        "rdc": 0.5,
        "sc": 0,
        "rsc": 0
    },
    {
        "filename": ".\\TemplatePathStack.php",
        "name": ".\\TemplatePathStack.php",
        "loc": 247,
        "logicalLoc": 42,
        "volume": 1896.58,
        "length": 300,
        "vocabulary": 80,
        "effort": 47554.37,
        "difficulty": "25.07",
        "time": 2642,
        "bugs": 0.63,
        "intelligentContent": 75.64,
        "maintainabilityIndexWithoutComment": "38.41",
        "maintainabilityIndex": "80.75",
        "commentWeight": 42.34,
        "instability": 0.75,
        "afferentCoupling": 1,
        "efferentCoupling": 3,
        "noc": 1,
        "noca": 0,
        "nocc": 1,
        "noc-anon": 0,
        "noi": 0,
        "nom": 11,
        "cyclomaticComplexity": 24,
        "myerInterval": "24:27",
        "myerDistance": 3,
        "operators": 3,
        "lcom": 1,
        "sysc": 19.67,
        "rsysc": 1.79,
        "dc": 11.67,
        "rdc": 1.06,
        "sc": 8,
        "rsc": 0.73
    },
    {
        "filename": ".\\TemplateResolver.php",
        "name": ".\\TemplateResolver.php",
        "loc": 42,
        "logicalLoc": 2,
        "volume": 18.09,
        "length": 7,
        "vocabulary": 6,
        "effort": 9.05,
        "difficulty": "0.5",
        "time": 1,
        "bugs": 0.01,
        "intelligentContent": 36.19,
        "maintainabilityIndexWithoutComment": "84.49",
        "maintainabilityIndex": "133.88",
        "commentWeight": 49.39,
        "instability": 0,
        "afferentCoupling": 0,
        "efferentCoupling": 0,
        "noc": 1,
        "noca": 1,
        "nocc": 0,
        "noc-anon": 0,
        "noi": 1,
        "nom": 1,
        "cyclomaticComplexity": 1,
        "myerInterval": "1:1",
        "myerDistance": 0,
        "operators": 0,
        "lcom": 0,
        "sysc": 1,
        "rsysc": 1,
        "dc": 1,
        "rdc": 1,
        "sc": 0,
        "rsc": 0
    },
    {
        "filename": ".\\Variables.php",
        "name": ".\\Variables.php",
        "loc": 328,
        "logicalLoc": 51,
        "volume": 2269.65,
        "length": 357,
        "vocabulary": 82,
        "effort": 66738.4,
        "difficulty": "29.4",
        "time": 3708,
        "bugs": 0.76,
        "intelligentContent": 77.19,
        "maintainabilityIndexWithoutComment": "36.97",
        "maintainabilityIndex": "80.95",
        "commentWeight": 43.98,
        "instability": 0.67,
        "afferentCoupling": 1,
        "efferentCoupling": 2,
        "noc": 1,
        "noca": 0,
        "nocc": 1,
        "noc-anon": 0,
        "noi": 0,
        "nom": 16,
        "cyclomaticComplexity": 17,
        "myerInterval": "17:17",
        "myerDistance": 0,
        "operators": 0,
        "lcom": 2,
        "sysc": 29,
        "rsysc": 1.81,
        "dc": 23,
        "rdc": 1.44,
        "sc": 6,
        "rsc": 0.38
    },
    {
        "filename": ".\\View.php",
        "name": ".\\View.php",
        "loc": 0,
        "logicalLoc": 0,
        "volume": 0,
        "length": 0,
        "vocabulary": 0,
        "effort": 0,
        "difficulty": "0",
        "time": 0,
        "bugs": 0,
        "intelligentContent": 0,
        "maintainabilityIndexWithoutComment": "171",
        "maintainabilityIndex": "171",
        "commentWeight": 0,
        "instability": 0,
        "afferentCoupling": 0,
        "efferentCoupling": 0,
        "noc": 0,
        "noca": 0,
        "nocc": 0,
        "noc-anon": 0,
        "noi": 0,
        "nom": 0,
        "cyclomaticComplexity": 1,
        "myerInterval": "1:1",
        "myerDistance": 0,
        "operators": 0,
        "lcom": 0,
        "sysc": 0,
        "rsysc": 0,
        "dc": 0,
        "rdc": 0,
        "sc": 0,
        "rsc": 0
    },
    {
        "filename": ".\\ViewEngine.php",
        "name": ".\\ViewEngine.php",
        "loc": 0,
        "logicalLoc": 0,
        "volume": 0,
        "length": 0,
        "vocabulary": 0,
        "effort": 0,
        "difficulty": "0",
        "time": 0,
        "bugs": 0,
        "intelligentContent": 0,
        "maintainabilityIndexWithoutComment": "171",
        "maintainabilityIndex": "171",
        "commentWeight": 0,
        "instability": 0,
        "afferentCoupling": 0,
        "efferentCoupling": 0,
        "noc": 0,
        "noca": 0,
        "nocc": 0,
        "noc-anon": 0,
        "noi": 0,
        "nom": 0,
        "cyclomaticComplexity": 1,
        "myerInterval": "1:1",
        "myerDistance": 0,
        "operators": 0,
        "lcom": 0,
        "sysc": 0,
        "rsysc": 0,
        "dc": 0,
        "rdc": 0,
        "sc": 0,
        "rsc": 0
    }
]