[
    {
        "filename": ".\\PhabricatorApplicationEditEngine.php",
        "name": ".\\PhabricatorApplicationEditEngine.php",
        "loc": 779,
        "logicalLoc": 184,
        "volume": 12577.97,
        "length": 1579,
        "vocabulary": 250,
        "effort": 501169.07,
        "difficulty": "39.84",
        "time": 27843,
        "bugs": 4.19,
        "intelligentContent": 315.67,
        "maintainabilityIndexWithoutComment": "15.57",
        "maintainabilityIndex": "44.85",
        "commentWeight": 29.28,
        "instability": 1,
        "afferentCoupling": 0,
        "efferentCoupling": 28,
        "noc": 1,
        "noca": 1,
        "nocc": 0,
        "noc-anon": 0,
        "noi": 0,
        "nom": 35,
        "cyclomaticComplexity": 47,
        "myerInterval": "47:47",
        "myerDistance": 0,
        "operators": 0,
        "lcom": 1,
        "sysc": 1054.67,
        "rsysc": 30.13,
        "dc": 39.67,
        "rdc": 1.13,
        "sc": 1015,
        "rsc": 29
    }
]