[
    {
        "filename": ".\\Application.php",
        "name": ".\\Application.php",
        "loc": 146,
        "logicalLoc": 17,
        "volume": 856.54,
        "length": 151,
        "vocabulary": 51,
        "effort": 13936.08,
        "difficulty": "16.27",
        "time": 774,
        "bugs": 0.29,
        "intelligentContent": 52.64,
        "maintainabilityIndexWithoutComment": "51.95",
        "maintainabilityIndex": "95.69",
        "commentWeight": 43.74,
        "instability": 1,
        "afferentCoupling": 0,
        "efferentCoupling": 3,
        "noc": 1,
        "noca": 0,
        "nocc": 1,
        "noc-anon": 0,
        "noi": 0,
        "nom": 9,
        "cyclomaticComplexity": 5,
        "myerInterval": "5:5",
        "myerDistance": 0,
        "operators": 0,
        "lcom": 8,
        "sysc": 12.5,
        "rsysc": 1.39,
        "dc": 6.5,
        "rdc": 0.72,
        "sc": 6,
        "rsc": 0.67
    },
    {
        "filename": ".\\Controller.php",
        "name": ".\\Controller.php",
        "loc": 18,
        "logicalLoc": 1,
        "volume": 16.25,
        "length": 7,
        "vocabulary": 5,
        "effort": 12.19,
        "difficulty": "0.75",
        "time": 1,
        "bugs": 0.01,
        "intelligentContent": 21.67,
        "maintainabilityIndexWithoutComment": "91.39",
        "maintainabilityIndex": "139.07",
        "commentWeight": 47.68,
        "instability": 0,
        "afferentCoupling": 0,
        "efferentCoupling": 0,
        "noc": 1,
        "noca": 0,
        "nocc": 1,
        "noc-anon": 0,
        "noi": 0,
        "nom": 0,
        "cyclomaticComplexity": 1,
        "myerInterval": "1:1",
        "myerDistance": 0,
        "operators": 0,
        "lcom": 0,
        "sysc": 0,
        "rsysc": 0,
        "dc": 0,
        "rdc": 0,
        "sc": 0,
        "rsc": 0
    },
    {
        "filename": ".\\Html.php",
        "name": ".\\Html.php",
        "loc": 975,
        "logicalLoc": 142,
        "volume": 11692.07,
        "length": 1633,
        "vocabulary": 143,
        "effort": 993330.51,
        "difficulty": "84.96",
        "time": 55185,
        "bugs": 3.9,
        "intelligentContent": 137.62,
        "maintainabilityIndexWithoutComment": "14.21",
        "maintainabilityIndex": "59.13",
        "commentWeight": 44.92,
        "instability": 0.75,
        "afferentCoupling": 1,
        "efferentCoupling": 3,
        "noc": 1,
        "noca": 0,
        "nocc": 1,
        "noc-anon": 0,
        "noi": 0,
        "nom": 37,
        "cyclomaticComplexity": 77,
        "myerInterval": "77:93",
        "myerDistance": 16,
        "operators": 16,
        "lcom": 37,
        "sysc": 60.83,
        "rsysc": 1.64,
        "dc": 24.83,
        "rdc": 0.67,
        "sc": 36,
        "rsc": 0.97
    },
    {
        "filename": ".\\HttpCache.php",
        "name": ".\\HttpCache.php",
        "loc": 132,
        "logicalLoc": 26,
        "volume": 1173.09,
        "length": 202,
        "vocabulary": 56,
        "effort": 21897.6,
        "difficulty": "18.67",
        "time": 1217,
        "bugs": 0.39,
        "intelligentContent": 62.84,
        "maintainabilityIndexWithoutComment": "45.49",
        "maintainabilityIndex": "89.36",
        "commentWeight": 43.87,
        "instability": 1,
        "afferentCoupling": 0,
        "efferentCoupling": 1,
        "noc": 1,
        "noca": 0,
        "nocc": 1,
        "noc-anon": 0,
        "noi": 0,
        "nom": 4,
        "cyclomaticComplexity": 16,
        "myerInterval": "16:23",
        "myerDistance": 7,
        "operators": 7,
        "lcom": 1,
        "sysc": 10,
        "rsysc": 2.5,
        "dc": 8,
        "rdc": 2,
        "sc": 2,
        "rsc": 0.5
    },
    {
        "filename": ".\\User.php",
        "name": ".\\User.php",
        "loc": 807,
        "logicalLoc": 146,
        "volume": 10574.06,
        "length": 1404,
        "vocabulary": 185,
        "effort": 585489.59,
        "difficulty": "55.37",
        "time": 32527,
        "bugs": 3.52,
        "intelligentContent": 190.97,
        "maintainabilityIndexWithoutComment": "15.33",
        "maintainabilityIndex": "58.89",
        "commentWeight": 43.56,
        "instability": 0.88,
        "afferentCoupling": 1,
        "efferentCoupling": 7,
        "noc": 1,
        "noca": 0,
        "nocc": 1,
        "noc-anon": 0,
        "noi": 0,
        "nom": 39,
        "cyclomaticComplexity": 69,
        "myerInterval": "69:83",
        "myerDistance": 14,
        "operators": 14,
        "lcom": 1,
        "sysc": 76.17,
        "rsysc": 1.95,
        "dc": 41.17,
        "rdc": 1.06,
        "sc": 35,
        "rsc": 0.9
    }
]