[
    {
        "filename": ".\\access.php",
        "name": ".\\access.php",
        "loc": 1082,
        "logicalLoc": 236,
        "volume": 15631.1,
        "length": 2043,
        "vocabulary": 201,
        "effort": 1388973.94,
        "difficulty": "88.86",
        "time": 77165,
        "bugs": 5.21,
        "intelligentContent": 175.91,
        "maintainabilityIndexWithoutComment": "5.02",
        "maintainabilityIndex": "44.96",
        "commentWeight": 39.94,
        "instability": 0.75,
        "afferentCoupling": 3,
        "efferentCoupling": 9,
        "noc": 1,
        "noca": 0,
        "nocc": 1,
        "noc-anon": 0,
        "noi": 0,
        "nom": 19,
        "cyclomaticComplexity": 103,
        "myerInterval": "103:119",
        "myerDistance": 16,
        "operators": 16,
        "lcom": 19,
        "sysc": 122.93,
        "rsysc": 6.47,
        "dc": 20.93,
        "rdc": 1.1,
        "sc": 102,
        "rsc": 5.37
    },
    {
        "filename": ".\\application.php",
        "name": ".\\application.php",
        "loc": 751,
        "logicalLoc": 200,
        "volume": 15061.72,
        "length": 1949,
        "vocabulary": 212,
        "effort": 783288.14,
        "difficulty": "52.01",
        "time": 43516,
        "bugs": 5.02,
        "intelligentContent": 289.62,
        "maintainabilityIndexWithoutComment": "9.66",
        "maintainabilityIndex": "43.19",
        "commentWeight": 33.53,
        "instability": 1,
        "afferentCoupling": 0,
        "efferentCoupling": 19,
        "noc": 1,
        "noca": 0,
        "nocc": 1,
        "noc-anon": 0,
        "noi": 0,
        "nom": 7,
        "cyclomaticComplexity": 81,
        "myerInterval": "81:107",
        "myerDistance": 26,
        "operators": 26,
        "lcom": 5,
        "sysc": 333.74,
        "rsysc": 47.68,
        "dc": 5.74,
        "rdc": 0.82,
        "sc": 328,
        "rsc": 46.86
    },
    {
        "filename": ".\\rules.php",
        "name": ".\\rules.php",
        "loc": 436,
        "logicalLoc": 125,
        "volume": 7866.1,
        "length": 1147,
        "vocabulary": 116,
        "effort": 423430.72,
        "difficulty": "53.83",
        "time": 23524,
        "bugs": 2.62,
        "intelligentContent": 146.13,
        "maintainabilityIndexWithoutComment": "20.12",
        "maintainabilityIndex": "57.87",
        "commentWeight": 37.75,
        "instability": 1,
        "afferentCoupling": 0,
        "efferentCoupling": 9,
        "noc": 1,
        "noca": 0,
        "nocc": 1,
        "noc-anon": 0,
        "noi": 0,
        "nom": 5,
        "cyclomaticComplexity": 51,
        "myerInterval": "51:61",
        "myerDistance": 10,
        "operators": 10,
        "lcom": 3,
        "sysc": 60.46,
        "rsysc": 12.09,
        "dc": 4.46,
        "rdc": 0.89,
        "sc": 56,
        "rsc": 11.2
    }
]