[
    {
        "filename": ".\\ClassLoader.php",
        "name": ".\\ClassLoader.php",
        "loc": 412,
        "logicalLoc": 65,
        "volume": 4775.25,
        "length": 732,
        "vocabulary": 92,
        "effort": 224178.5,
        "difficulty": "46.95",
        "time": 12454,
        "bugs": 1.59,
        "intelligentContent": 101.72,
        "maintainabilityIndexWithoutComment": "29.45",
        "maintainabilityIndex": "67.78",
        "commentWeight": 38.33,
        "instability": 1,
        "afferentCoupling": 0,
        "efferentCoupling": 1,
        "noc": 1,
        "noca": 0,
        "nocc": 1,
        "noc-anon": 0,
        "noi": 0,
        "nom": 20,
        "cyclomaticComplexity": 39,
        "myerInterval": "39:41",
        "myerDistance": 2,
        "operators": 2,
        "lcom": 4,
        "sysc": 36.5,
        "rsysc": 1.83,
        "dc": 34.5,
        "rdc": 1.73,
        "sc": 2,
        "rsc": 0.1
    }
]